[
  {
    "id": "f1a2b3c4-d5e6-7890-1234-567890abcdef",
    "client_id": "a1b2c3d4-e5f6-7890-1234-567890abcdef",
    "title": "Recover Cloud Infrastructure with AWS",
    "description": "Comprehensive guide for restoring EC2 instances, Elastic Load Balancers, RDS snapshots, and DNS records from Route53 after infrastructure failure.",
    "is_template": false,
    "created_by": "1c6e6c13-a18c-4d7c-9e35-68bbdd5dff41",
    "created_at": "2025-01-20T10:00:00.000000+00:00",
    "updated_at": "2025-06-21T00:52:17.669Z",
    "app_id": null,
    "template_name": null,
    "template_description": null
  },
  {
    "id": "g2b3c4d5-e6f7-8901-2345-678901bcdefg",
    "client_id": "a1b2c3d4-e5f6-7890-1234-567890abcdef",
    "title": "Data Center Power Outage Recovery",
    "description": "Step-by-step guide for restarting on-premises equipment, verifying UPS/generator usage, and restoring connectivity after power outage.",
    "is_template": false,
    "created_by": "1c6e6c13-a18c-4d7c-9e35-68bbdd5dff41",
    "created_at": "2025-01-20T10:00:00.000000+00:00",
    "updated_at": "2025-01-20T10:00:00.000000+00:00",
    "app_id": null,
    "template_name": null,
    "template_description": null
  },
  {
    "id": "h3c4d5e6-f7g8-9012-3456-789012cdefgh",
    "client_id": "b2c3d4e5-f6g7-8901-2345-678901bcdefg",
    "title": "Restore Production PostgreSQL from Snapshot",
    "description": "Instructions for identifying the correct backup, restoring to a new instance, and syncing with production environment.",
    "is_template": false,
    "created_by": "1c6e6c13-a18c-4d7c-9e35-68bbdd5dff41",
    "created_at": "2025-01-20T10:00:00.000000+00:00",
    "updated_at": "2025-01-20T10:00:00.000000+00:00",
    "app_id": null,
    "template_name": null,
    "template_description": null
  },
  {
    "id": "i4d5e6f7-g8h9-0123-4567-890123defghi",
    "client_id": "b2c3d4e5-f6g7-8901-2345-678901bcdefg",
    "title": "Failover to Read Replica in Case of Master DB Failure",
    "description": "Promotes a replica to master, updates connection strings, and verifies application connectivity during database failover.",
    "is_template": false,
    "created_by": "1c6e6c13-a18c-4d7c-9e35-68bbdd5dff41",
    "created_at": "2025-01-20T10:00:00.000000+00:00",
    "updated_at": "2025-01-20T10:00:00.000000+00:00",
    "app_id": null,
    "template_name": null,
    "template_description": null
  },
  {
    "id": "j5e6f7g8-h9i0-1234-5678-901234efghij",
    "client_id": "c3d4e5f6-g7h8-9012-3456-789012cdefgh",
    "title": "Redeploy Critical Microservices from Scratch",
    "description": "Rebuild and deploy all essential services using Docker/Kubernetes with fallback to specific Git commit hashes.",
    "is_template": false,
    "created_by": "1c6e6c13-a18c-4d7c-9e35-68bbdd5dff41",
    "created_at": "2025-01-20T10:00:00.000000+00:00",
    "updated_at": "2025-01-20T10:00:00.000000+00:00",
    "app_id": null,
    "template_name": null,
    "template_description": null
  },
  {
    "id": "k6f7g8h9-i0j1-2345-6789-012345fghijk",
    "client_id": "c3d4e5f6-g7h8-9012-3456-789012cdefgh",
    "title": "Rollback to Last Known Good Deployment",
    "description": "CI/CD-based rollback with canary monitoring, health checks, and logs validation to restore service stability.",
    "is_template": false,
    "created_by": "1c6e6c13-a18c-4d7c-9e35-68bbdd5dff41",
    "created_at": "2025-01-20T10:00:00.000000+00:00",
    "updated_at": "2025-01-20T10:00:00.000000+00:00",
    "app_id": null,
    "template_name": null,
    "template_description": null
  },
  {
    "id": "l7g8h9i0-j1k2-3456-7890-123456ghijkl",
    "client_id": "d4e5f6g7-h8i9-0123-4567-890123defghi",
    "title": "Respond to Ransomware Attack",
    "description": "Isolate affected systems, activate forensics tooling, restore clean backups, and notify stakeholders during ransomware incident.",
    "is_template": false,
    "created_by": "1c6e6c13-a18c-4d7c-9e35-68bbdd5dff41",
    "created_at": "2025-01-20T10:00:00.000000+00:00",
    "updated_at": "2025-01-20T10:00:00.000000+00:00",
    "app_id": null,
    "template_name": null,
    "template_description": null
  },
  {
    "id": "m8h9i0j1-k2l3-4567-8901-234567hijklm",
    "client_id": "d4e5f6g7-h8i9-0123-4567-890123defghi",
    "title": "Rotate All User Credentials After Breach",
    "description": "Guides password and API key rotation across all internal systems, with priority levels by risk after security breach.",
    "is_template": false,
    "created_by": "1c6e6c13-a18c-4d7c-9e35-68bbdd5dff41",
    "created_at": "2025-01-20T10:00:00.000000+00:00",
    "updated_at": "2025-01-20T10:00:00.000000+00:00",
    "app_id": null,
    "template_name": null,
    "template_description": null
  }
]